{
  "db_name": "PostgreSQL",
  "query": "select column_name from information_schema.columns\n            where table_name='equipment_items'\n              and column_name in ('status','submitted_by','approved_at','created_at')\n            order by column_name",
  "describe": {
    "columns": [
      {
        "ordinal": 0,
        "name": "column_name",
        "type_info": "Name"
      }
    ],
    "parameters": {
      "Left": []
    },
    "nullable": [
      true
    ]
  },
  "hash": "ef0cb184099a53ca4ac0ef09a9e11d90cd6391f2891fa876c6f06ea72ebfbf4d"
}
