{
  "db_name": "PostgreSQL",
  "query": "select brand, model, variant from equipment_items where id = $1",
  "describe": {
    "columns": [
      {
        "ordinal": 0,
        "name": "brand",
        "type_info": "Text"
      },
      {
        "ordinal": 1,
        "name": "model",
        "type_info": "Text"
      },
      {
        "ordinal": 2,
        "name": "variant",
        "type_info": "Text"
      }
    ],
    "parameters": {
      "Left": [
        "Uuid"
      ]
    },
    "nullable": [
      false,
      false,
      true
    ]
  },
  "hash": "29a9bfd2befd5f94d2ec96e033d471c73fa25c768da441396cf0855aba06a71e"
}
