{
  "db_name": "PostgreSQL",
  "query": "select si.role, ei.display_name, ei.canonical_name\n             from setup_items si\n             join equipment_items ei on ei.id = si.item_id\n            where si.setup_id = $1\n            order by si.role, ei.canonical_name",
  "describe": {
    "columns": [
      {
        "ordinal": 0,
        "name": "role",
        "type_info": "Text"
      },
      {
        "ordinal": 1,
        "name": "display_name",
        "type_info": "Text"
      },
      {
        "ordinal": 2,
        "name": "canonical_name",
        "type_info": "Text"
      }
    ],
    "parameters": {
      "Left": [
        "Uuid"
      ]
    },
    "nullable": [
      false,
      false,
      false
    ]
  },
  "hash": "f1e9cec8e4cfa3f963d843ebe1ae39cc63699d9590ae3dfec2f94dd688d41735"
}
